{ "apacheActiveMQ":"[1]",
 "apacheActiveMQProtocols":"[4]",
 "apacheActiveMQExample":"[5]",
 "apacheActiveMQJMS":"[2]",
 "acpacheAtiveMQPlatforms":"[3]",
 "apacheApollo":"[6]",
 "apacheApolloPlatforms":"[7]",
 "apacheApolloExamples":"[8]",
 "apacheKafkaLicense":"[9]",
 "apacheKafkaPlatforms":"[10]",
 "apacheKafkaExample":"[11]",
 "apacheQpiProtocols":"[17]",
 "apacheQpidPlatforms":"[16]",
 "apacheQpidLicense":"[15]",
 "apacheQpidJMS":"[13]",
 "apacheQpidJMSExamples":"[14]",
 "apacheQpidCPPExamples":"[12]",
 "beanstalkdLicense":"[18]",
 "beanstalkdProtocols":"[20]",
 "beanstalkdPlatforms":"[19]",
 "celeryLicense":"[22]",
 "celeryBackend":"[21]",
 "celeryExamples":"[23]",
 "chronicleQueueLicense":"[25]",
 "chronicleQueueExamples":"[24]",
 "chronicleQueuePlatforms":"[26]",
 "darnerLicense":"[27]",
 "darnerPlatforms":"[28]",
 "darnerProtocols":"[29]",
 "delayedJobLicense":"[30]",
 "delayedJobPlatforms":"[31]",
 "disqueLicense":"[32]",
 "disqueProtocol":"[33]",
 "eclipseMosquittoExamples":"[34]",
 "eclipseMosquittoLicense":"[35]",
 "eclipseMosquittoProtocol":"[37]",
 "eclipseMosquittoPlatforms":"[36]",
 "eclipseOm2mLicense":"[38]",
 "ffmqLicense":"[40]",
 "ffmqHomepage":"[39]",
 "gearmanLicense":"[42]",
 "gearmanExamples":"[41]",
 "gearmanPlatforms":"[43]",
 "gearmanProtocols":"[44]",
 "hornetQLicense":"[46]",
 "hornetQProtocol":"[48]",
 "hornetQPlatforms":"[47]",
 "hornetQExamples":"[45]",
 "hueyLicense":"[51]",
 "hueyBackend":"[49]",
 "hueyExamples":"[50]",
 "kestrelLicense":"[53]",
 "kestrelProtocols":"[55]",
 "kestrelExample":"[52]",
 "kestrelPlatforms":"[54]",
 "kueLicense":"[57]",
 "kueExamples":"[56]",
 "mappedbusLicense":"[60]",
 "mappedBusExamples":"[59]",
 "mappedBusPlatforms":"[61]",
 "messageBusLicense":"[64]",
 "messageBusExamples":"[63]",
 "messageBusProtocol":"[62]",
 "messageBusBackend":"[58]",
 "rabbitMQLicense":"[67]",
 "rabbitMQProtocols":"[69]",
 "rabbitMQPlatforms":"[68]",
 "rabbitMQExamples":"[65]",
 "rabbitMQJMS":"[66]",
 "redisLicense":"[72]",
 "redisPlatforms":"[73]",
 "redisCluster":"[70]",
 "redisProtocol":"[74]",
 "redisExamples":"[71]",
 "resqueExamples":"[75]",
 "resqueLicense":"[76]",
 "rqLicense":"[79]",
 "rqExample":"[78]",
 "rqBackend":"[77]",
 "siberiteLicense":"[80]",
 "siberiteProtocol":"[82]",
 "siberitePlatforms":"[81]",
 "sidekiqBackend":"[83]",
 "sidekiqLicense":"[84]",
 "zeroMqExample":"[85]",
 "zeroMQLicense":"[87]",
 "zeroMQPlatforms":"[88]",
 "zeroMQJMS":"[86]" }